{
  "project_info": {
    "project_number": "87521488436",
    "project_id": "e-commerce-248c0",
    "storage_bucket": "e-commerce-248c0.firebasestorage.app"
  },
  "client": [
    {
      "client_info": {
        "mobilesdk_app_id": "1:87521488436:android:adab787ae11a7b4fc56461",
        "android_client_info": {
          "package_name": "com.example.trendtrove"
        }
      },
      "oauth_client": [],
      "api_key": [
        {
          "current_key": "AIzaSyCKlKVi0AmFx5Go91xNpRQCHbKyM9icoJ4"
        }
      ],
      "services": {
        "appinvite_service": {
          "other_platform_oauth_client": []
        }
      }
    }
  ],
  "configuration_version": "1"
}